[
    {
      "name": "国际幻诸葛亮",
      "image": "/packs/overseas/images/os_if__zhugeliang.jpg",
      "faction": "蜀",
      "health": 4,
      "startingHealth": 3,
      "skills": [
        {
          "skillName": "北定",
          "skillDescription": "一名角色的准备阶段开始时，你可以声明并记录至多X种未被〖北定〗记录过的基本牌或普通锦囊牌牌名。若如此做，此回合的弃牌阶段结束时，你视为依次使用本回合记录的牌（无距离限制），若此牌的目标不包含当前回合角色，其摸一张牌（X为你的体力值）。"
        },
        {
          "skillName": "竭虑",
          "skillDescription": "锁定技，一名角色的回合结束时，若你于本回合内未对其使用过牌，则你失去1点体力；当你受到1点伤害或失去1点体力后，若你的体力上限小于7，则你加1点体力上限。"
        },
        {
          "skillName": "魂游",
          "skillDescription": "限定技，当你处于濒死状态时，你可以将体力回复至1点，本回合防止你受到的伤害和失去体力。此回合结束时，你“入幻”并获得一个额外的回合。"
        },
      
        {
          "skillName": "幻-北定",
          "skillDescription": "你使用〖北定〗记录的牌无距离限制且不计入次数；当你使用〖北定〗记录牌名的牌结算结束后，你摸一张牌，然后移除〖北定〗记录中的此牌名。"
        },
        {
          "skillName": "幻-竭虑",
          "skillDescription": "锁定技，当你减1点体力上限后，你回复1点体力。"
        },
        {
          "skillName": "幻-幻计",
          "skillDescription": "出牌阶段限一次，你可以减1点体力上限，在〖北定〗记录中增加X种牌名（X为你的体力值）。"
        },
        {
          "skillName": "幻-怅归",
          "skillDescription": "锁定技，结束阶段开始时，若你的体力值为全场最低，则你“退幻”并将体力上限调整至体力值。"
        }
      ]
    },
    {
      "name": "国际幻赵云",
      "image": "/packs/overseas/images/os_if__zhaoyun.jpg",
      "faction": "蜀",
      "health": 4,
      "skills": [
        {
          "skillName": "竭战",
          "skillDescription": "其他角色的出牌阶段开始时，若其在你攻击范围内，你可摸一张牌，然后其视为对你使用一张无距离限制且计入次数限制的【杀】。"
        },
        {
          "skillName": "龙烬",
          "skillDescription": "觉醒技，当你进入濒死状态时，你将体力回复至2点，然后于此回合与之后的五个回合内，你视为拥有〖龙胆〗和〖冲阵〗，且你至其他角色的距离视为1。"
        }
      ]
    },
    {
      "name": "国际幻张郃",
      "image": "/packs/overseas/images/os_if__zhanghe.jpg",
      "faction": "魏",
      "health": 4,
      "skills": [
        {
          "skillName": "溃端",
          "skillDescription": "锁定技，当你使用【杀】指定唯一目标后，你与其各将随机两张手牌标记为“溃端”牌（只能当【杀】使用或打出）。当“溃端”牌造成伤害时，若伤害来源拥有的“溃端”牌数大于受到伤害的角色，则此伤害+1。“溃端”牌暂实现为锁定视为技"
        }
      ]
    },
    {
      "name": "国际幻诸葛果",
      "image": "/packs/overseas/images/os_if__zhugeguo.jpg",
      "faction": "蜀",
      "gender": "女",
      "health": 3,
      "startingHealth": 3,
      "skills": [
        {
          "skillName": "仙援",
          "skillDescription": "①每轮开始时，你获得2枚“仙援”。（一名角色至多有3枚“仙缘”）②出牌阶段，你可以将任意枚“仙援”分配给其他角色。③有“仙援”的角色出牌阶段开始时，你选择一项：1. 观看其手牌，将其中至多X张牌以任意顺序置于牌堆顶；2. 其摸X张牌。（X为其“仙援”数）然后若此时不是你的回合，你移除其所有“仙援”。"
        },
        {
          "skillName": "灵隐",
          "skillDescription": "当你成为普通锦囊牌的目标后，你可以亮出牌堆顶的一张牌，若此牌与此普通锦囊牌颜色相同，你获得亮出的牌，若花色也相同，此普通锦囊牌对此目标无效。"
        }
      ]
    },
    {
      "name": "国际幻姜维",
      "image": "/packs/overseas/images/os_if__jiangwei.jpg",
      "faction": "蜀",
      "health": 4,
      "skills": [
        {
          "skillName": "擎汉",
          "skillDescription": "①出牌阶段限一次，你可用一张装备牌与一名角色拼点：若你赢，你可视为对其使用一张以其为唯一目标的普通锦囊牌；若两张拼点牌颜色相同，你与其获得对方的拼点牌。②你的拼点牌点数+X（X为你装备区牌数的两倍）。"
        },
        {
          "skillName": "治宦",
          "skillDescription": "当你使用【杀】造成伤害时，你可防止此伤害并选择一项：1. 获得其装备区里的一张牌；2. 获得并使用一张牌堆或弃牌堆中与你空置的装备栏对应类型的装备牌。若如此做，其下次使用【闪】时随机弃置两张手牌。"
        }
      ]
    },
    {
      "name": "国际幻司马懿",
      "image": "/packs/overseas/images/os_if__simayi.jpg",
      "faction": "魏",
      "health": 3,
      "skills": [
        {
          "skillName": "纵权",
          "skillDescription": "准备阶段或结束阶段，你可以选择一名角色，然后你进行判定：若结果为红色，你令其摸一张牌；若结果为黑色，你令其弃置一张牌；若你本次与上一次发动〖纵权〗所选择的目标角色相同但结果颜色不同，则改为摸/弃置三张牌。若如此做，你令一名角色获得判定牌。"
        },
        {
          "skillName": "鬼谋",
          "skillDescription": "每回合限两次，当一名角色的判定牌生效前，你可观看牌堆底的四张牌，选择其中一张牌代替之，然后将其余牌以任意顺序置于牌堆顶。"
        }
      ]
    },
    {
      "name": "国际幻魏延",
      "image": "/packs/overseas/images/os_if__weiyan.jpg",
      "faction": "蜀",
      "health": 4,
      "skills": [
        {
          "skillName": "奇击",
          "skillDescription": "出牌阶段开始时，你可以视为对一名其他角色使用X张无距离限制且不计入次数的【杀】，此【杀】指定目标时，其可以选择一名本回合未以此法选择过的其他角色，被选择的角色摸一张牌，然后其可以将此【杀】的目标转移给自己（X为出牌阶段开始时你手牌的类别数）。"
        },
        {
          "skillName": "偏狂",
          "skillDescription": "锁定技，当你使用【杀】对目标角色造成伤害时，若你本回合使用【杀】造成过伤害，此伤害+1。你的回合内，当你使用【杀】结算后，若此【杀】未造成伤害，本回合你手牌上限-1。"
        }
      ]
    },
    {
      "name": "国际幻刘禅",
      "image": "/packs/overseas/images/os_if__liushan.jpg",
      "faction": "蜀",
      "health": 3,
      "skills": [
        {
          "skillName": "归汉",
          "skillDescription": "出牌阶段限一次，你可以选择至多三名有手牌的其他角色，然后展示牌堆顶牌，这些角色依次选择一项：1.将一张同类别牌置于牌堆顶；2.失去1点体力。然后你选择一项：1.摸X张牌；2.获得牌堆第X+1张开始的两张牌。（X为以此法置于牌堆顶的牌数）"
        },
        {
          "skillName": "任贤",
          "skillDescription": "出牌阶段限一次，你可以将除【闪】以外的所有基本牌交给一名其他角色，此回合结束后，其执行一个只有出牌阶段的额外回合，该回合内其只能使用或打出你以此法交给其的牌且使用【杀】无次数限制。"
        },
        {
          "skillName": "延祚",
          "skillDescription": "主公技，锁定技，每回合限两次，当其他蜀势力角色于“任贤”回合内造成伤害后，你摸两张牌。"
        }
      ]
    },
    {
      "name": "国际幻陆逊",
      "image": "/packs/overseas/images/os_if__luxun.jpg",
      "faction": "吴",
      "health": 3,
      "skills": [
        {
          "skillName": "砺锋",
          "skillDescription": "出牌阶段，你可以弃置两张点数不同的牌，对一名距离X以内的角色造成1点伤害（X为这两张牌点数之差），其受到此伤害时，可以重铸一张手牌（没有手牌则改为摸一张牌），若此牌点数介于这两张牌点数闭区间，防止此伤害且本回合此技能失效。"
        },
        {
          "skillName": "逆涡",
          "skillDescription": "出牌阶段开始时，你可以选择一名其他角色，选择你与其等量的手牌，本回合你与其不能使用或打出这些牌。"
        }
      ]
    },
    {
      "name": "国际幻曹昂",
      "image": "/packs/overseas/images/os_if__caoang.jpg",
      "faction": "魏",
      "health": 3,
      "skills": [
        {
          "skillName": "炽灰",
          "skillDescription": "其他角色的回合开始时，你可以废除一个装备栏，选择：1.弃置其区域里的一张牌；2.将牌堆里的一张对应副类别的牌置入其装备区。若如此做，你失去1点体力，摸X张牌（X为你已损失的体力值且至多为2）。"
        },
        {
          "skillName": "赴曦",
          "skillDescription": "持恒技，当你进入濒死状态时，或你的装备栏均被废除后，你可以选择一至两项并“入幻”并将体力回复至体力上限：1.获得一个额外回合；2.此次“入幻”时保留〖炽灰〗；3.将手牌摸至X张（X为你的体力上限且至多为5）；4.恢复所有装备栏（你的装备栏均被废除时方可选择此项）。"
        },
     
        {
          "skillName": "幻-煌烛",
          "skillDescription": "准备阶段，你可以选择一个已被废除的装备栏，从牌堆或弃牌堆中随机获得一张对应副类别的装备牌（若无则随机获得一张装备牌），并记录此牌牌名。出牌阶段开始时，你可以选择或变更至多两个已记录且对应装备栏已被废除的装备牌牌名（每种副类别限一个），视为拥有这些装备牌的技能直到此装备栏被恢复。"
        },
        {
          "skillName": "幻-离渊",
          "skillDescription": "你可以将一张对应装备栏已被废除的装备牌当普【杀】使用或打出（无距离、次数限制，不计次数）。当你以此法使用或打出牌时，你摸一张牌。"
        },
        {
          "skillName": "幻-冀筏",
          "skillDescription": "锁定技，当你进入濒死状态时，你减X点体力上限（X为你上次发动〖赴曦〗时选择的项数），选择此次“退幻”时保留〖煌烛〗或〖离渊〗，然后“退幻”并将体力回复至体力上限。"
        }
      ]
    }
  ]