[
    {
      "name": "刘伶",
      "image": "packs/mini/images/liuling.jpg",
      "faction": "群",
      "gender": "男",
      "health": 3,
      "skills": [
        {
          "skillName": "酒颂",
          "skillDescription": "①你可将一张锦囊牌当【酒】使用。②当一名角色使用【酒】时，你获得1枚“醉”。（“醉”至多3枚）"
        },
        {
          "skillName": "酕醄",
          "skillDescription": "当其他角色使用牌时，若目标数为1且没有处于濒死状态的角色，你可弃1枚“醉”，若此牌有其他合法目标，令此牌改为随机指定一个合法目标（不受距离限制），否则你从牌堆中获得一张锦囊牌。"
        },
        {
          "skillName": "避仕",
          "skillDescription": "锁定技，你不能成为伤害类锦囊牌的目标。"
        }
      ]
    },
    {
      "name": "王戎",
      "image": "packs/mini/images/wangrong.jpg",
      "faction": "魏",
      "gender": "男",
      "health": 3,
      "skills": [
        {
          "skillName": "俭吝",
          "skillDescription": "一名角色的回合结束后，若你本回合有基本牌因使用、打出或弃置而进入弃牌堆，你可以选择其中一张获得之。"
        },
        {
          "skillName": "死孝",
          "skillDescription": "游戏开始时，你选择一名其他角色。每名角色的回合限一次，当其需要使用除【无懈可击】以外的牌时，其可以观看你的手牌，并可以选择其中一张牌使用之，然后你摸一张牌。"
        }
      ]
    },
    {
      "name": "向秀",
      "image": "packs/mini/images/xiangxiu.jpg",
      "faction": "魏",
      "gender": "男",
      "health": 3,
      "skills": [
        {
          "skillName": "妙析",
          "skillDescription": "出牌阶段限一次，你可以选择一名其他角色，与其同时展示一张手牌，若这些牌：颜色相同，你获得其的展示牌；类别相同，其失去1点体力；点数相同，〖妙析〗视为未发动且此项本回合失效。"
        },
        {
          "skillName": "思旧",
          "skillDescription": "每轮结束时，若你本轮获得过其他角色的牌，你可以摸一张牌并观看一名其他角色的手牌。"
        }
      ]
    }
  ]